jeremypy/__init__.py
jeremypy/jeremy_config.py
jeremypy/jeremy_csv.py
jeremypy/jeremy_driver.py
jeremypy/jeremy_exceptions.py
jeremypy/jeremy_json.py
jeremypy/jeremy_string.py
jeremypy/jeremy_twitter.py
JeremyPy-0.6.0.dist-info/LICENSE
JeremyPy-0.6.0.dist-info/METADATA
JeremyPy-0.6.0.dist-info/WHEEL
JeremyPy-0.6.0.dist-info/top_level.txt
JeremyPy-0.6.0.dist-info/RECORD
